TaskFormatter/TaskFormatter.py
TaskFormatter/__init__.py
TaskFormatter-1.0.2.dist-info/METADATA
TaskFormatter-1.0.2.dist-info/WHEEL
TaskFormatter-1.0.2.dist-info/top_level.txt
TaskFormatter-1.0.2.dist-info/RECORD
