Metadata-Version: 2.1
Name: TaskFormatter
Version: 1.0.2
Summary: A Python package for function execution status and spinner output
Home-page: https://github.com/seanssmith/TaskFormatter
Author: Sean Smith
Author-email: sean@ssmith.app
Classifier: Programming Language :: Python :: 3
Classifier: License :: OSI Approved :: MIT License
Classifier: Operating System :: OS Independent
Requires-Python: >=3.6
